{
  "arch": "x86_64",
  "build": "py312hecd8cb5_0",
  "build_number": 0,
  "channel": "https://repo.anaconda.com/pkgs/main/osx-64/",
  "constrains": [],
  "depends": [
    "python >=3.12,<3.13.0a0",
    "setuptools",
    "wheel"
  ],
  "fn": "pip-24.2-py312hecd8cb5_0.conda",
  "license": "MIT",
  "license_family": "MIT",
  "md5": "35119ef238299ccf29b25889fd466139",
  "name": "pip",
  "platform": "darwin",
  "sha256": "f0401476a4262ec46825548535f9510db4aa1d46b8a5992aac210760a69ddda3",
  "size": 2912965,
  "subdir": "osx-64",
  "timestamp": 1723484719000,
  "url": "https://repo.anaconda.com/pkgs/main/osx-64/pip-24.2-py312hecd8cb5_0.conda",
  "version": "24.2"
}